wikipedia_cli/__init__.py
wikipedia_cli/console.py
wikipedia_cli/wikipedia.py
wikipedia_cli_by_ss-0.3.0.dist-info/entry_points.txt
wikipedia_cli_by_ss-0.3.0.dist-info/LICENSE
wikipedia_cli_by_ss-0.3.0.dist-info/WHEEL
wikipedia_cli_by_ss-0.3.0.dist-info/METADATA
wikipedia_cli_by_ss-0.3.0.dist-info/RECORD
